coast_search/__init__.py
coast_search/_version.py
coast_search/query_generator.py
coast_search/search.py
coast_search/utils.py
coast_search-1.0.0.dist-info/METADATA
coast_search-1.0.0.dist-info/RECORD
coast_search-1.0.0.dist-info/WHEEL
coast_search-1.0.0.dist-info/top_level.txt
