Metadata-Version: 2.1
Name: coast-search
Version: 1.0.0
Summary: Search functionality of COAST
Home-page: https://github.com/zedrem/coast_search
Author: Ashley Williams
Author-email: ashley.williams@pg.canterbury.ac.nz
License: MIT license
Keywords: coast_search
Platform: UNKNOWN
Classifier: Development Status :: 5 - Production/Stable
Classifier: Intended Audience :: Developers
Classifier: Intended Audience :: Education
Classifier: Intended Audience :: Science/Research
Classifier: License :: OSI Approved :: MIT License
Classifier: Natural Language :: English
Classifier: Programming Language :: Python :: 3.5
Classifier: Programming Language :: Python :: 3.6
Requires-Dist: randomwords
Requires-Dist: google-api-python-client
